{"assets":{"E857BD603F7117228C43533A0180CA60":{"type":"texture","index":4,"assetRequest":{"type":"slide","state":"contents","slide":"none"},"url":{"native":"assets\/81669789-9D4E-46F7-8C01-F782BB559689.pdf"},"width":1026,"height":19},"73CDDF1532160B82087D02DFB58251FF":{"type":"texture","index":14,"assetRequest":{"type":"slide","state":"contents","slide":"none"},"url":{"native":"assets\/81669789-9D4E-46F7-8C01-F782BB559689.pdf"},"width":900,"height":44},"19D39F26BBF3E99701402A4CD6C8EC2E":{"type":"texture","index":6,"assetRequest":{"type":"slide","state":"contents","slide":"none"},"url":{"native":"assets\/81669789-9D4E-46F7-8C01-F782BB559689.pdf"},"width":45,"height":14},"FC4FEE615C6DD4F71D0AF1DA00C8E4DF":{"type":"texture","index":16,"assetRequest":{"type":"slide","state":"contents","slide":"none"},"url":{"native":"assets\/81669789-9D4E-46F7-8C01-F782BB559689.pdf"},"width":1027,"height":94},"57C6ABAACAB1520BA4F51129C02428B9":{"type":"texture","index":18,"assetRequest":{"type":"slide","state":"contents","slide":"none"},"url":{"native":"assets\/81669789-9D4E-46F7-8C01-F782BB559689.pdf"},"width":375,"height":373},"6D3BD730611AEDBDFF24E556B047938C":{"type":"texture","index":22,"assetRequest":{"type":"slide","state":"contents","slide":"none"},"url":{"native":"assets\/81669789-9D4E-46F7-8C01-F782BB559689.pdf"},"width":393,"height":537},"7997E8F06BC201E039EF065E93082D88":{"type":"texture","index":1,"assetRequest":{"type":"slide","state":"contents","slide":"none"},"url":{"native":"assets\/81669789-9D4E-46F7-8C01-F782BB559689.pdf"},"width":1003,"height":44},"3AF23A742D6F1B28B161D01517090E4F":{"type":"texture","index":3,"assetRequest":{"type":"slide","state":"contents","slide":"none"},"url":{"native":"assets\/81669789-9D4E-46F7-8C01-F782BB559689.pdf"},"width":61,"height":15},"D652167B412906357E3CE351B7717F53":{"type":"texture","index":17,"assetRequest":{"type":"slide","state":"contents","slide":"none"},"url":{"native":"assets\/81669789-9D4E-46F7-8C01-F782BB559689.pdf"},"width":151,"height":35},"E7ED5F39F9B284E3C82B24F9FA28837A":{"type":"texture","index":11,"assetRequest":{"type":"slide","state":"contents","slide":"none"},"url":{"native":"assets\/81669789-9D4E-46F7-8C01-F782BB559689.pdf"},"width":355,"height":44},"B3ECAFF3A25943E1D6C4CCDF2DB4608C":{"type":"texture","index":10,"assetRequest":{"type":"slide","state":"contents","slide":"none"},"url":{"native":"assets\/81669789-9D4E-46F7-8C01-F782BB559689.pdf"},"width":328,"height":43},"6F35A2FA386A392D32E7D14B03912335":{"type":"texture","index":7,"assetRequest":{"type":"slide","state":"contents","slide":"none"},"url":{"native":"assets\/81669789-9D4E-46F7-8C01-F782BB559689.pdf"},"width":191,"height":34},"A859F6D6A591DE66D362599897966C1B":{"type":"texture","index":13,"assetRequest":{"type":"slide","state":"contents","slide":"none"},"url":{"native":"assets\/81669789-9D4E-46F7-8C01-F782BB559689.pdf"},"width":916,"height":43},"A6B3E55D8D49AFA75C517C767C9F662E":{"type":"texture","index":2,"assetRequest":{"type":"slide","state":"contents","slide":"none"},"url":{"native":"assets\/81669789-9D4E-46F7-8C01-F782BB559689.pdf"},"width":429,"height":43},"9B9E3FF61C6DA97BCFC9137737E378E4":{"type":"texture","index":19,"assetRequest":{"type":"slide","state":"contents","slide":"none"},"url":{"native":"assets\/81669789-9D4E-46F7-8C01-F782BB559689.pdf"},"width":483,"height":43},"F0EA3E4D0366E990238DA02E9BD07BA6":{"type":"texture","index":24,"assetRequest":{"type":"slide","state":"contents","slide":"none"},"url":{"native":"assets\/81669789-9D4E-46F7-8C01-F782BB559689.pdf"},"width":355,"height":44},"CAFED3AF2045F50E77B4C5EF057C0296":{"type":"texture","index":20,"assetRequest":{"type":"slide","state":"contents","slide":"none"},"url":{"native":"assets\/81669789-9D4E-46F7-8C01-F782BB559689.pdf"},"width":502,"height":43},"9E64784E33ED2E40F3E357CC4DCE638C":{"type":"texture","index":21,"assetRequest":{"type":"slide","state":"contents","slide":"none"},"url":{"native":"assets\/81669789-9D4E-46F7-8C01-F782BB559689.pdf"},"width":428,"height":285},"5C7BF4DB61D4F8109096B2599DB2A9D9":{"type":"texture","index":12,"assetRequest":{"type":"slide","state":"contents","slide":"none"},"url":{"native":"assets\/81669789-9D4E-46F7-8C01-F782BB559689.pdf"},"width":292,"height":43},"C7AA257A4E5C6ADFC46D47F49821002A":{"type":"texture","index":23,"assetRequest":{"type":"slide","state":"contents","slide":"none"},"url":{"native":"assets\/81669789-9D4E-46F7-8C01-F782BB559689.pdf"},"width":328,"height":43},"7BF16B539769317ED1409CCE8CBC5605":{"type":"texture","index":9,"assetRequest":{"type":"slide","state":"contents","slide":"none"},"url":{"native":"assets\/81669789-9D4E-46F7-8C01-F782BB559689.pdf"},"width":394,"height":537},"923CA22559BCC412D89FDB110EC58F93":{"type":"texture","index":5,"assetRequest":{"type":"slide","state":"contents","slide":"none"},"url":{"native":"assets\/81669789-9D4E-46F7-8C01-F782BB559689.pdf"},"width":1026,"height":7},"498E23C82CA78A4BCD7BA88E5243B6FC":{"type":"texture","index":0,"assetRequest":{"type":"slide","state":"contents","slide":"none"},"url":{"native":"assets\/81669789-9D4E-46F7-8C01-F782BB559689.pdf"},"width":1024,"height":768},"D8677BC1273213678DD6CACBA39C3DD2":{"type":"texture","index":8,"assetRequest":{"type":"slide","state":"contents","slide":"none"},"url":{"native":"assets\/81669789-9D4E-46F7-8C01-F782BB559689.pdf"},"width":427,"height":285},"C8739BB44A636A445C17349105AF9D78":{"type":"texture","index":25,"assetRequest":{"type":"slide","state":"contents","slide":"none"},"url":{"native":"assets\/81669789-9D4E-46F7-8C01-F782BB559689.pdf"},"width":916,"height":43},"50A60D786241F61E51AC87B06DB956ED":{"type":"texture","index":15,"assetRequest":{"type":"slide","state":"contents","slide":"none"},"url":{"native":"assets\/81669789-9D4E-46F7-8C01-F782BB559689.pdf"},"width":846,"height":565}},"events":[{"effects":[{"beginTime":0,"baseLayer":{"animations":[],"initialState":{"affineTransform":[1,0,0,1,0,0],"masksToBounds":false,"rotation":0,"scale":1,"position":{"pointX":512,"pointY":384},"width":1024,"sublayerTransform":[1,0,0,0,0,1,0,0,0,0,1,0,0,0,0,1],"contentsRect":{"y":0,"x":0,"width":1,"height":1},"opacity":1,"edgeAntialiasingMask":251658240,"height":768,"hidden":false,"anchorPoint":{"pointX":0.5,"pointY":0.5}},"objectID":"0","layers":[{"animations":[],"initialState":{"affineTransform":[1,0,0,1,0,0],"masksToBounds":false,"rotation":0,"scale":1,"position":{"pointX":512,"pointY":384},"width":1024,"sublayerTransform":[1,0,0,0,0,1,0,0,0,0,1,-0.00049229876906403734,0,0,0,1],"contentsRect":{"y":0,"x":0,"width":1,"height":1},"opacity":1,"edgeAntialiasingMask":251658240,"height":768,"hidden":false,"anchorPoint":{"pointX":0.5,"pointY":0.5}},"layers":[{"animations":[{"timeOffset":0,"beginTime":0,"repeatCount":0,"animations":[{"timeOffset":0,"from":{"scalar":0},"beginTime":0,"repeatCount":0,"fillMode":"both","duration":1,"autoreverses":false,"timingFunction":"EaseInEaseOut","property":"zPosition","to":{"scalar":0}}],"fillMode":"both","autoreverses":false,"duration":1}],"initialState":{"affineTransform":[1,0,0,1,0,0],"masksToBounds":false,"rotation":0,"scale":1,"position":{"pointX":512,"pointY":384},"width":1024,"sublayerTransform":[1,0,0,0,0,1,0,0,0,0,1,0,0,0,0,1],"contentsRect":{"y":0,"x":0,"width":1,"height":1},"opacity":1,"edgeAntialiasingMask":251658240,"height":768,"hidden":false,"anchorPoint":{"pointX":0.5,"pointY":0.5}},"layers":[{"animations":[],"layers":[],"texturedRectangle":{"isBackgroundTexture":true,"singleTextureOpacity":1,"textureType":1,"textBaseline":0,"textXHeight":0,"isVerticalText":false},"initialState":{"affineTransform":[1,0,0,1,0,0],"masksToBounds":false,"rotation":0,"scale":1,"position":{"pointX":512,"pointY":384},"width":1024,"sublayerTransform":[1,0,0,0,0,1,0,0,0,0,1,0,0,0,0,1],"contentsRect":{"y":0,"x":0,"width":1,"height":1},"opacity":1,"edgeAntialiasingMask":0,"height":768,"hidden":false,"anchorPoint":{"pointX":0.5,"pointY":0.5}},"texture":"498E23C82CA78A4BCD7BA88E5243B6FC"}]}]},{"animations":[{"timeOffset":0,"beginTime":0,"repeatCount":0,"animations":[{"timeOffset":0,"from":{"scalar":0.001},"beginTime":0,"repeatCount":0,"fillMode":"both","duration":1,"autoreverses":false,"timingFunction":"EaseInEaseOut","property":"zPosition","to":{"scalar":0.001}}],"fillMode":"both","autoreverses":false,"duration":1}],"initialState":{"affineTransform":[1,0,0,1,0,0],"masksToBounds":false,"rotation":0,"scale":1,"position":{"pointX":511.99999995400589,"pointY":108.86780360686166},"width":1024.9600410461426,"sublayerTransform":[1,0,0,0,0,1,0,0,0,0,1,0,0,0,0,1],"contentsRect":{"y":0,"x":0,"width":1,"height":1},"opacity":1,"edgeAntialiasingMask":251658240,"height":117.99999475479126,"hidden":false,"anchorPoint":{"pointX":0.5,"pointY":0.5}},"layers":[{"animations":[{"timeOffset":0,"beginTime":0,"repeatCount":0,"animations":[{"timeOffset":0,"from":{"scalar":1},"beginTime":0,"repeatCount":0,"fillMode":"forwards","duration":0.33329999999999999,"autoreverses":false,"timingFunction":"EaseInEaseOut","property":"opacity","to":{"scalar":0}},{"timeOffset":0,"from":{"scalar":true},"beginTime":0.33329999999999999,"repeatCount":0,"fillMode":"forwards","property":"hidden","autoreverses":false,"duration":0.66670000000000007,"to":{"scalar":true}}],"fillMode":"both","autoreverses":false,"duration":1}],"layers":[],"texturedRectangle":{"singleTextureOpacity":1,"textXHeight":0.41999999999999998,"textBaseline":0.75517985571229607,"isBackgroundTexture":true,"isVerticalText":false,"textColor":[0,0,0,1],"textureType":6},"initialState":{"affineTransform":[1,0,0,1,0,0],"masksToBounds":false,"rotation":0,"scale":1,"position":{"pointX":512.48000000000002,"pointY":59},"width":1003,"sublayerTransform":[1,0,0,0,0,1,0,0,0,0,1,0,0,0,0,1],"contentsRect":{"y":0,"x":0,"width":1,"height":1},"opacity":1,"edgeAntialiasingMask":0,"height":44,"hidden":false,"anchorPoint":{"pointX":0.5054835288444014,"pointY":1.0879046870333189}},"texture":"7997E8F06BC201E039EF065E93082D88"}]},{"animations":[{"timeOffset":0,"beginTime":0,"repeatCount":0,"animations":[{"timeOffset":0,"from":{"scalar":0.002},"beginTime":0,"repeatCount":0,"fillMode":"both","duration":1,"autoreverses":false,"timingFunction":"EaseInEaseOut","property":"zPosition","to":{"scalar":0.002}}],"fillMode":"both","autoreverses":false,"duration":1}],"initialState":{"affineTransform":[1,0,0,1,0,0],"masksToBounds":false,"rotation":0,"scale":1,"position":{"pointX":511.99999995400589,"pointY":108.86780360686166},"width":1024.9600410461426,"sublayerTransform":[1,0,0,0,0,1,0,0,0,0,1,0,0,0,0,1],"contentsRect":{"y":0,"x":0,"width":1,"height":1},"opacity":1,"edgeAntialiasingMask":251658240,"height":117.99999475479126,"hidden":false,"anchorPoint":{"pointX":0.5,"pointY":0.5}},"layers":[{"animations":[{"timeOffset":0,"beginTime":0,"repeatCount":0,"animations":[{"timeOffset":0,"from":{"scalar":1},"beginTime":0,"repeatCount":0,"fillMode":"forwards","duration":0.33329999999999999,"autoreverses":false,"timingFunction":"EaseInEaseOut","property":"opacity","to":{"scalar":0}},{"timeOffset":0,"from":{"scalar":true},"beginTime":0.33329999999999999,"repeatCount":0,"fillMode":"forwards","property":"hidden","autoreverses":false,"duration":0.66670000000000007,"to":{"scalar":true}}],"fillMode":"both","autoreverses":false,"duration":1}],"layers":[],"texturedRectangle":{"singleTextureOpacity":1,"textXHeight":0.42976744186046512,"textBaseline":0.74948636398467505,"isBackgroundTexture":true,"isVerticalText":false,"textColor":[0,0,0,1],"textureType":6},"initialState":{"affineTransform":[1,0,0,1,0,0],"masksToBounds":false,"rotation":0,"scale":1,"position":{"pointX":512.48000000000002,"pointY":59},"width":429,"sublayerTransform":[1,0,0,0,0,1,0,0,0,0,1,0,0,0,0,1],"contentsRect":{"y":0,"x":0,"width":1,"height":1},"opacity":1,"edgeAntialiasingMask":0,"height":43,"hidden":false,"anchorPoint":{"pointX":1.1841491362026448,"pointY":-0.18912078536125521}},"texture":"A6B3E55D8D49AFA75C517C767C9F662E"}]},{"animations":[{"timeOffset":0,"beginTime":0,"repeatCount":0,"animations":[{"timeOffset":0,"from":{"scalar":0.0030000000000000001},"beginTime":0,"repeatCount":0,"fillMode":"both","duration":1,"autoreverses":false,"timingFunction":"EaseInEaseOut","property":"zPosition","to":{"scalar":0.0030000000000000001}}],"fillMode":"both","autoreverses":false,"duration":1}],"initialState":{"affineTransform":[1,0,0,1,0,0],"masksToBounds":false,"rotation":0,"scale":1,"position":{"pointX":32.901954650878906,"pointY":8.6121902465820312},"width":67.883998155593872,"sublayerTransform":[1,0,0,0,0,1,0,0,0,0,1,0,0,0,0,1],"contentsRect":{"y":0,"x":0,"width":1,"height":1},"opacity":1,"edgeAntialiasingMask":251658240,"height":27.000001072883606,"hidden":false,"anchorPoint":{"pointX":0.5,"pointY":0.5}},"layers":[{"animations":[{"timeOffset":0,"beginTime":0,"repeatCount":0,"animations":[{"timeOffset":0,"from":{"scalar":1},"beginTime":0,"repeatCount":0,"fillMode":"forwards","duration":0.33329999999999999,"autoreverses":false,"timingFunction":"EaseInEaseOut","property":"opacity","to":{"scalar":0}},{"timeOffset":0,"from":{"scalar":true},"beginTime":0.33329999999999999,"repeatCount":0,"fillMode":"forwards","property":"hidden","autoreverses":false,"duration":0.66670000000000007,"to":{"scalar":true}}],"fillMode":"both","autoreverses":false,"duration":1}],"layers":[],"texturedRectangle":{"singleTextureOpacity":1,"textXHeight":0.43119999999999997,"textBaseline":0.7992151538530986,"isBackgroundTexture":true,"isVerticalText":false,"textColor":[0,0,0,1],"textureType":6},"initialState":{"affineTransform":[1,0,0,1,0,0],"masksToBounds":false,"rotation":0,"scale":1,"position":{"pointX":33.942,"pointY":13.5},"width":61,"sublayerTransform":[1,0,0,0,0,1,0,0,0,0,1,0,0,0,0,1],"contentsRect":{"y":0,"x":0,"width":1,"height":1},"opacity":1,"edgeAntialiasingMask":0,"height":15,"hidden":false,"anchorPoint":{"pointX":0.50658943562429459,"pointY":0.50747931400934854}},"texture":"3AF23A742D6F1B28B161D01517090E4F"}]},{"animations":[{"timeOffset":0,"beginTime":0,"repeatCount":0,"animations":[{"timeOffset":0,"from":{"scalar":0.0040000000000000001},"beginTime":0,"repeatCount":0,"fillMode":"both","duration":1,"autoreverses":false,"timingFunction":"EaseInEaseOut","property":"zPosition","to":{"scalar":0.0040000000000000001}}],"fillMode":"both","autoreverses":false,"duration":1}],"initialState":{"affineTransform":[1,0,0,1,0,0],"masksToBounds":false,"rotation":0,"scale":1,"position":{"pointX":511.99998772144312,"pointY":7.6676045656204224},"width":1023.4651489257814,"sublayerTransform":[1,0,0,0,0,1,0,0,0,0,1,0,0,0,0,1],"contentsRect":{"y":0,"x":0,"width":1,"height":1},"opacity":1,"edgeAntialiasingMask":251658240,"height":16.630849838256836,"hidden":false,"anchorPoint":{"pointX":0.5,"pointY":0.5}},"layers":[{"animations":[{"timeOffset":0,"beginTime":0,"repeatCount":0,"animations":[{"timeOffset":0,"from":{"texture":"E857BD603F7117228C43533A0180CA60"},"beginTime":0,"repeatCount":0,"fillMode":"both","duration":1,"autoreverses":false,"timingFunction":"EaseInEaseOut","property":"contents","to":{"texture":"E857BD603F7117228C43533A0180CA60"}}],"fillMode":"both","autoreverses":false,"duration":1}],"layers":[],"texturedRectangle":{"singleTextureOpacity":1,"textXHeight":0,"shapePath":{"lineWidth":1,"flatness":0.59999999999999998,"lineCapStyle":0,"elements":[{"type":"MoveToPoint","points":[[1.2674132585524376,1.3521796464920044]]},{"type":"AddLine","points":[[1024.7325621843338,1.3521796464920044]]},{"type":"AddLine","points":[[1024.7325621843338,17.98302948474884]]},{"type":"AddLine","points":[[1.2674132585524376,17.98302948474884]]},{"type":"CloseSubpath"},{"type":"MoveToPoint","points":[[1.2674132585524376,1.3521796464920044]]}],"windingRule":0,"lineJoinStyle":0,"miterLimit":10},"isBackgroundTexture":true,"textBaseline":0,"isVerticalText":false,"textureType":5},"initialState":{"affineTransform":[1,0,0,1,0,0],"masksToBounds":false,"rotation":0,"scale":1,"position":{"pointX":511.73257446289074,"pointY":8.315424919128418},"width":1026,"sublayerTransform":[1,0,0,0,0,1,0,0,0,0,1,0,0,0,0,1],"contentsRect":{"y":0,"x":0,"width":1,"height":1},"opacity":1,"edgeAntialiasingMask":0,"height":19,"hidden":false,"anchorPoint":{"pointX":0.49999998803259571,"pointY":0.50882129292739064}},"texture":"E857BD603F7117228C43533A0180CA60"}]},{"animations":[{"timeOffset":0,"beginTime":0,"repeatCount":0,"animations":[{"timeOffset":0,"from":{"scalar":0.0050000000000000001},"beginTime":0,"repeatCount":0,"fillMode":"both","duration":1,"autoreverses":false,"timingFunction":"EaseInEaseOut","property":"zPosition","to":{"scalar":0.0050000000000000001}}],"fillMode":"both","autoreverses":false,"duration":1}],"initialState":{"affineTransform":[1,0,0,1,0,0],"masksToBounds":false,"rotation":0,"scale":1,"position":{"pointX":511.99999502301216,"pointY":17.612190008163452},"width":1023.4338989257812,"sublayerTransform":[1,0,0,0,0,1,0,0,0,0,1,0,0,0,0,1],"contentsRect":{"y":0,"x":0,"width":1,"height":1},"opacity":1,"edgeAntialiasingMask":251658240,"height":4.6500544548034686,"hidden":false,"anchorPoint":{"pointX":0.5,"pointY":0.5}},"layers":[{"animations":[{"timeOffset":0,"beginTime":0,"repeatCount":0,"animations":[{"timeOffset":0,"from":{"texture":"923CA22559BCC412D89FDB110EC58F93"},"beginTime":0,"repeatCount":0,"fillMode":"both","duration":1,"autoreverses":false,"timingFunction":"EaseInEaseOut","property":"contents","to":{"texture":"923CA22559BCC412D89FDB110EC58F93"}}],"fillMode":"both","autoreverses":false,"duration":1}],"layers":[],"texturedRectangle":{"singleTextureOpacity":1,"textXHeight":0,"shapePath":{"lineWidth":1,"flatness":0.59999999999999998,"lineCapStyle":0,"elements":[{"type":"MoveToPoint","points":[[1.2830455601215363,1.287162780761717]]},{"type":"AddLine","points":[[1024.7169444859028,1.287162780761717]]},{"type":"AddLine","points":[[1024.7169444859028,5.9372172355651855]]},{"type":"AddLine","points":[[1.2830455601215363,5.9372172355651855]]},{"type":"CloseSubpath"},{"type":"MoveToPoint","points":[[1.2830455601215363,1.287162780761717]]}],"windingRule":0,"lineJoinStyle":0,"miterLimit":10},"isBackgroundTexture":true,"textBaseline":0,"isVerticalText":false,"textureType":5},"initialState":{"affineTransform":[1,0,0,1,0,0],"masksToBounds":false,"rotation":0,"scale":1,"position":{"pointX":511.71694946289062,"pointY":2.3250272274017352},"width":1026,"sublayerTransform":[1,0,0,0,0,1,0,0,0,0,1,0,0,0,0,1],"contentsRect":{"y":0,"x":0,"width":1,"height":1},"opacity":1,"edgeAntialiasingMask":0,"height":7,"hidden":false,"anchorPoint":{"pointX":0.49999999514913468,"pointY":0.51602714402335026}},"texture":"923CA22559BCC412D89FDB110EC58F93"}]},{"animations":[{"timeOffset":0,"beginTime":0,"repeatCount":0,"animations":[{"timeOffset":0,"from":{"scalar":0.0060000000000000001},"beginTime":0,"repeatCount":0,"fillMode":"both","duration":1,"autoreverses":false,"timingFunction":"EaseInEaseOut","property":"zPosition","to":{"scalar":0.0060000000000000001}}],"fillMode":"both","autoreverses":false,"duration":1}],"initialState":{"affineTransform":[1,0,0,1,0,0],"masksToBounds":false,"rotation":0,"scale":1,"position":{"pointX":27.248954296112061,"pointY":9.6121902465820312},"width":82.319998741149902,"sublayerTransform":[1,0,0,0,0,1,0,0,0,0,1,0,0,0,0,1],"contentsRect":{"y":0,"x":0,"width":1,"height":1},"opacity":1,"edgeAntialiasingMask":251658240,"height":22.200042009353638,"hidden":false,"anchorPoint":{"pointX":0.5,"pointY":0.5}},"layers":[{"animations":[{"timeOffset":0,"beginTime":0,"repeatCount":0,"animations":[{"timeOffset":0,"from":{"texture":"19D39F26BBF3E99701402A4CD6C8EC2E"},"beginTime":0,"repeatCount":0,"fillMode":"both","duration":1,"autoreverses":false,"timingFunction":"EaseInEaseOut","property":"contents","to":{"texture":"19D39F26BBF3E99701402A4CD6C8EC2E"}}],"fillMode":"both","autoreverses":false,"duration":1}],"layers":[],"texturedRectangle":{"singleTextureOpacity":1,"textXHeight":0.50700000000000001,"textBaseline":0.83430646998541691,"isBackgroundTexture":true,"isVerticalText":false,"textColor":[0.81037485599517822,0.69284248352050781,0.229374960064888,1],"textureType":6},"initialState":{"affineTransform":[1,0,0,1,0,0],"masksToBounds":false,"rotation":0,"scale":1,"position":{"pointX":41.159999847412109,"pointY":11.100021362304688},"width":45,"sublayerTransform":[1,0,0,0,0,1,0,0,0,0,1,0,0,0,0,1],"contentsRect":{"y":0,"x":0,"width":1,"height":1},"opacity":1,"edgeAntialiasingMask":0,"height":14,"hidden":false,"anchorPoint":{"pointX":0.49442121717664933,"pointY":0.61515647172927856}},"texture":"19D39F26BBF3E99701402A4CD6C8EC2E"}]},{"animations":[{"timeOffset":0,"beginTime":0,"repeatCount":0,"animations":[{"timeOffset":0,"from":{"scalar":0.0070000000000000001},"beginTime":0,"repeatCount":0,"fillMode":"both","duration":1,"autoreverses":false,"timingFunction":"EaseInEaseOut","property":"zPosition","to":{"scalar":0.0080000000000000002}}],"fillMode":"both","autoreverses":false,"duration":1}],"initialState":{"affineTransform":[1,0,0,1,0,0],"masksToBounds":false,"rotation":0,"scale":1,"position":{"pointX":501.42003516390469,"pointY":-681.67416593350288},"width":1024.9600410461426,"sublayerTransform":[1,0,0,0,0,1,0,0,0,0,1,0,0,0,0,1],"contentsRect":{"y":0,"x":0,"width":1,"height":1},"opacity":1,"edgeAntialiasingMask":251658240,"height":117.99999475479126,"hidden":false,"anchorPoint":{"pointX":0.5,"pointY":0.5}},"layers":[{"animations":[{"timeOffset":0,"beginTime":0,"repeatCount":0,"animations":[{"timeOffset":0,"from":{"scalar":0},"beginTime":0.66670000000000007,"repeatCount":0,"fillMode":"both","duration":0.33329999999999999,"autoreverses":false,"timingFunction":"EaseInEaseOut","property":"opacity","to":{"scalar":1}},{"timeOffset":0,"from":{"scalar":false},"beginTime":0.66670000000000007,"repeatCount":0,"fillMode":"forwards","property":"hidden","autoreverses":false,"duration":0.33329999999999993,"to":{"scalar":false}}],"fillMode":"both","autoreverses":false,"duration":1}],"layers":[],"texturedRectangle":{"singleTextureOpacity":1,"textXHeight":0.41999999999999998,"textBaseline":0.74286236615855661,"isBackgroundTexture":true,"isVerticalText":false,"textColor":[0,0,0,1],"textureType":6},"initialState":{"affineTransform":[1,0,0,1,0,0],"masksToBounds":false,"rotation":0,"scale":1,"position":{"pointX":512.48000000000002,"pointY":59},"width":1003,"sublayerTransform":[1,0,0,0,0,1,0,0,0,0,1,0,0,0,0,1],"contentsRect":{"y":0,"x":0,"width":1,"height":1},"opacity":1,"edgeAntialiasingMask":0,"height":44,"hidden":true,"anchorPoint":{"pointX":0.50590230771768041,"pointY":1.0755871974795794}},"texture":"7997E8F06BC201E039EF065E93082D88"}]},{"animations":[{"timeOffset":0,"beginTime":0,"repeatCount":0,"animations":[{"timeOffset":0,"from":{"scalar":0.0080000000000000002},"beginTime":0,"repeatCount":0,"fillMode":"both","duration":1,"autoreverses":false,"timingFunction":"EaseInEaseOut","property":"zPosition","to":{"scalar":0.0090000000000000011}}],"fillMode":"both","autoreverses":false,"duration":1}],"initialState":{"affineTransform":[1,0,0,1,0,0],"masksToBounds":false,"rotation":0,"scale":1,"position":{"pointX":501.42003516390469,"pointY":-681.67416593350288},"width":1024.9600410461426,"sublayerTransform":[1,0,0,0,0,1,0,0,0,0,1,0,0,0,0,1],"contentsRect":{"y":0,"x":0,"width":1,"height":1},"opacity":1,"edgeAntialiasingMask":251658240,"height":117.99999475479126,"hidden":false,"anchorPoint":{"pointX":0.5,"pointY":0.5}},"layers":[{"animations":[{"timeOffset":0,"beginTime":0,"repeatCount":0,"animations":[{"timeOffset":0,"from":{"scalar":0},"beginTime":0.66670000000000007,"repeatCount":0,"fillMode":"both","duration":0.33329999999999999,"autoreverses":false,"timingFunction":"EaseInEaseOut","property":"opacity","to":{"scalar":1}},{"timeOffset":0,"from":{"scalar":false},"beginTime":0.66670000000000007,"repeatCount":0,"fillMode":"forwards","property":"hidden","autoreverses":false,"duration":0.33329999999999993,"to":{"scalar":false}}],"fillMode":"both","autoreverses":false,"duration":1}],"layers":[],"texturedRectangle":{"singleTextureOpacity":1,"textXHeight":0.54352941176470593,"textBaseline":0.93193953267577923,"isBackgroundTexture":true,"isVerticalText":false,"textColor":[0,0,0,1],"textureType":6},"initialState":{"affineTransform":[1,0,0,1,0,0],"masksToBounds":false,"rotation":0,"scale":1,"position":{"pointX":512.48000000000002,"pointY":59},"width":191,"sublayerTransform":[1,0,0,0,0,1,0,0,0,0,1,0,0,0,0,1],"contentsRect":{"y":0,"x":0,"width":1,"height":1},"opacity":1,"edgeAntialiasingMask":0,"height":34,"hidden":true,"anchorPoint":{"pointX":2.661884893407505,"pointY":-0.25512245032054431}},"texture":"6F35A2FA386A392D32E7D14B03912335"}]},{"animations":[{"timeOffset":0,"beginTime":0,"repeatCount":0,"animations":[{"timeOffset":0,"from":{"scalar":0.0090000000000000011},"beginTime":0,"repeatCount":0,"fillMode":"both","duration":1,"autoreverses":false,"timingFunction":"EaseInEaseOut","property":"zPosition","to":{"scalar":0.01}}],"fillMode":"both","autoreverses":false,"duration":1}],"initialState":{"affineTransform":[1,0,0,1,0,0],"masksToBounds":false,"rotation":0,"scale":1,"position":{"pointX":273.47342562986165,"pointY":342.69007777039855},"width":424.82192993164062,"sublayerTransform":[1,0,0,0,0,1,0,0,0,0,1,0,0,0,0,1],"contentsRect":{"y":0,"x":0,"width":1,"height":1},"opacity":1,"edgeAntialiasingMask":251658240,"height":281.875,"hidden":false,"anchorPoint":{"pointX":0.5,"pointY":0.5}},"layers":[{"animations":[{"timeOffset":0,"beginTime":0,"repeatCount":0,"animations":[{"timeOffset":0,"from":{"scalar":1},"beginTime":0,"repeatCount":0,"fillMode":"both","duration":1,"autoreverses":false,"timingFunction":"EaseInEaseOut","property":"transform.scale.x","to":{"scalar":1.0023419203747073}},{"timeOffset":0,"from":{"scalar":1},"beginTime":0,"repeatCount":0,"fillMode":"both","duration":1,"autoreverses":false,"timingFunction":"EaseInEaseOut","property":"transform.scale.y","to":{"scalar":1}},{"timeOffset":0,"from":{"texture":"D8677BC1273213678DD6CACBA39C3DD2"},"beginTime":0,"repeatCount":0,"fillMode":"both","duration":1,"autoreverses":false,"timingFunction":"EaseInEaseOut","property":"contents","to":{"texture":"9E64784E33ED2E40F3E357CC4DCE638C"}},{"timeOffset":0,"from":{"pointX":0,"pointY":0},"beginTime":0,"repeatCount":0,"fillMode":"both","duration":1,"autoreverses":false,"timingFunction":"EaseInEaseOut","property":"transform.translation","to":{"pointX":-10.500062235058806,"pointY":-790}}],"fillMode":"both","autoreverses":false,"duration":1}],"layers":[],"texturedRectangle":{"isBackgroundTexture":true,"singleTextureOpacity":1,"textureType":5,"textBaseline":0,"textXHeight":0,"isVerticalText":false},"initialState":{"affineTransform":[1,0,0,1,0,0],"masksToBounds":false,"rotation":0,"scale":1,"position":{"pointX":212.41096496582028,"pointY":140.93539712589518},"width":427,"sublayerTransform":[1,0,0,0,0,1,0,0,0,0,1,0,0,0,0,1],"contentsRect":{"y":0,"x":0,"width":1,"height":1},"opacity":1,"edgeAntialiasingMask":0,"height":285,"hidden":false,"anchorPoint":{"pointX":0.49993776494112802,"pointY":0.50065956103962705}},"texture":"D8677BC1273213678DD6CACBA39C3DD2"}]},{"animations":[{"timeOffset":0,"beginTime":0,"repeatCount":0,"animations":[{"timeOffset":0,"from":{"scalar":0.01},"beginTime":0,"repeatCount":0,"fillMode":"both","duration":1,"autoreverses":false,"timingFunction":"EaseInEaseOut","property":"zPosition","to":{"scalar":0.010999999999999999}}],"fillMode":"both","autoreverses":false,"duration":1}],"initialState":{"affineTransform":[1,0,0,1,0,0],"masksToBounds":false,"rotation":0,"scale":1,"position":{"pointX":756.90196558573302,"pointY":435.44875514731359},"width":390.43988037109386,"sublayerTransform":[1,0,0,0,0,1,0,0,0,0,1,0,0,0,0,1],"contentsRect":{"y":0,"x":0,"width":1,"height":1},"opacity":1,"edgeAntialiasingMask":251658240,"height":534.087158203125,"hidden":false,"anchorPoint":{"pointX":0.5,"pointY":0.5}},"layers":[{"animations":[{"timeOffset":0,"beginTime":0,"repeatCount":0,"animations":[{"timeOffset":0,"from":{"scalar":1},"beginTime":0,"repeatCount":0,"fillMode":"both","duration":1,"autoreverses":false,"timingFunction":"EaseInEaseOut","property":"transform.scale.x","to":{"scalar":0.9974619289340102}},{"timeOffset":0,"from":{"scalar":1},"beginTime":0,"repeatCount":0,"fillMode":"both","duration":1,"autoreverses":false,"timingFunction":"EaseInEaseOut","property":"transform.scale.y","to":{"scalar":1}},{"timeOffset":0,"from":{"texture":"7BF16B539769317ED1409CCE8CBC5605"},"beginTime":0.33330000000000004,"repeatCount":0,"fillMode":"both","duration":0.66669999999999996,"autoreverses":false,"timingFunction":"EaseInEaseOut","property":"contents","to":{"texture":"6D3BD730611AEDBDFF24E556B047938C"}},{"timeOffset":0,"from":{"pointX":0,"pointY":0},"beginTime":0,"repeatCount":0,"fillMode":"both","duration":1,"autoreverses":false,"timingFunction":"EaseInEaseOut","property":"transform.translation","to":{"pointX":-10.499751181689817,"pointY":-791}}],"fillMode":"both","autoreverses":false,"duration":1}],"layers":[],"texturedRectangle":{"isBackgroundTexture":true,"singleTextureOpacity":1,"textureType":5,"textBaseline":0,"textXHeight":0,"isVerticalText":false},"initialState":{"affineTransform":[1,0,0,1,0,0],"masksToBounds":false,"rotation":0,"scale":1,"position":{"pointX":195.21994018554688,"pointY":267.0435791015625},"width":394,"sublayerTransform":[1,0,0,0,0,1,0,0,0,0,1,0,0,0,0,1],"contentsRect":{"y":0,"x":0,"width":1,"height":1},"opacity":1,"edgeAntialiasingMask":0,"height":537,"hidden":false,"anchorPoint":{"pointX":0.49975118168967742,"pointY":0.49990457196892663}},"texture":"7BF16B539769317ED1409CCE8CBC5605"}]},{"animations":[{"timeOffset":0,"beginTime":0,"repeatCount":0,"animations":[{"timeOffset":0,"from":{"scalar":0.010999999999999999},"beginTime":0,"repeatCount":0,"fillMode":"both","duration":1,"autoreverses":false,"timingFunction":"EaseInEaseOut","property":"zPosition","to":{"scalar":0.012}}],"fillMode":"both","autoreverses":false,"duration":1}],"initialState":{"affineTransform":[1,0,0,1,0,0],"masksToBounds":false,"rotation":0,"scale":1,"position":{"pointX":273.46871084659904,"pointY":612.01235384128404},"width":390.43989181518555,"sublayerTransform":[1,0,0,0,0,1,0,0,0,0,1,0,0,0,0,1],"contentsRect":{"y":0,"x":0,"width":1,"height":1},"opacity":1,"edgeAntialiasingMask":251658240,"height":188.99999856948853,"hidden":false,"anchorPoint":{"pointX":0.5,"pointY":0.5}},"layers":[{"animations":[{"timeOffset":0,"beginTime":0,"repeatCount":0,"animations":[{"timeOffset":0,"from":{"texture":"B3ECAFF3A25943E1D6C4CCDF2DB4608C"},"beginTime":0,"repeatCount":0,"fillMode":"both","duration":1,"autoreverses":false,"timingFunction":"EaseInEaseOut","property":"contents","to":{"texture":"C7AA257A4E5C6ADFC46D47F49821002A"}},{"timeOffset":0,"from":{"pointX":0,"pointY":0},"beginTime":0,"repeatCount":0,"fillMode":"both","duration":1,"autoreverses":false,"timingFunction":"EaseInEaseOut","property":"transform.translation","to":{"pointX":-11,"pointY":-791}}],"fillMode":"both","autoreverses":false,"duration":1}],"layers":[],"texturedRectangle":{"singleTextureOpacity":1,"textXHeight":0.42976744186046512,"textBaseline":0.74122004600964597,"isBackgroundTexture":true,"isVerticalText":false,"textColor":[0,0,0,1],"textureType":6},"initialState":{"affineTransform":[1,0,0,1,0,0],"masksToBounds":false,"rotation":0,"scale":1,"position":{"pointX":195.21994018554688,"pointY":94.5},"width":328,"sublayerTransform":[1,0,0,0,0,1,0,0,0,0,1,0,0,0,0,1],"contentsRect":{"y":0,"x":0,"width":1,"height":1},"opacity":1,"edgeAntialiasingMask":0,"height":43,"hidden":false,"anchorPoint":{"pointX":0.50142897903827177,"pointY":-1.0229684986851215}},"texture":"B3ECAFF3A25943E1D6C4CCDF2DB4608C"}]},{"animations":[{"timeOffset":0,"beginTime":0,"repeatCount":0,"animations":[{"timeOffset":0,"from":{"scalar":0.012},"beginTime":0,"repeatCount":0,"fillMode":"both","duration":1,"autoreverses":false,"timingFunction":"EaseInEaseOut","property":"zPosition","to":{"scalar":0.013000000000000001}}],"fillMode":"both","autoreverses":false,"duration":1}],"initialState":{"affineTransform":[1,0,0,1,0,0],"masksToBounds":false,"rotation":0,"scale":1,"position":{"pointX":273.46871084659904,"pointY":612.01235384128404},"width":390.43989181518555,"sublayerTransform":[1,0,0,0,0,1,0,0,0,0,1,0,0,0,0,1],"contentsRect":{"y":0,"x":0,"width":1,"height":1},"opacity":1,"edgeAntialiasingMask":251658240,"height":188.99999856948853,"hidden":false,"anchorPoint":{"pointX":0.5,"pointY":0.5}},"layers":[{"animations":[{"timeOffset":0,"beginTime":0,"repeatCount":0,"animations":[{"timeOffset":0,"from":{"texture":"E7ED5F39F9B284E3C82B24F9FA28837A"},"beginTime":0,"repeatCount":0,"fillMode":"both","duration":1,"autoreverses":false,"timingFunction":"EaseInEaseOut","property":"contents","to":{"texture":"F0EA3E4D0366E990238DA02E9BD07BA6"}},{"timeOffset":0,"from":{"pointX":0,"pointY":0},"beginTime":0,"repeatCount":0,"fillMode":"both","duration":1,"autoreverses":false,"timingFunction":"EaseInEaseOut","property":"transform.translation","to":{"pointX":-11,"pointY":-791}}],"fillMode":"both","autoreverses":false,"duration":1}],"layers":[],"texturedRectangle":{"singleTextureOpacity":1,"textXHeight":0.56727272727272726,"textBaseline":0.92001123193130174,"isBackgroundTexture":true,"isVerticalText":false,"textColor":[0.96236997842788696,0.82058531045913696,0.27432787418365479,1],"textureType":6},"initialState":{"affineTransform":[1,0,0,1,0,0],"masksToBounds":false,"rotation":0,"scale":1,"position":{"pointX":195.21994018554688,"pointY":94.5},"width":355,"sublayerTransform":[1,0,0,0,0,1,0,0,0,0,1,0,0,0,0,1],"contentsRect":{"y":0,"x":0,"width":1,"height":1},"opacity":1,"edgeAntialiasingMask":0,"height":44,"hidden":false,"anchorPoint":{"pointX":0.49991184542127642,"pointY":1.7957353308304496}},"texture":"E7ED5F39F9B284E3C82B24F9FA28837A"}]},{"animations":[{"timeOffset":0,"beginTime":0,"repeatCount":0,"animations":[{"timeOffset":0,"from":{"scalar":0.013000000000000001},"beginTime":0,"repeatCount":0,"fillMode":"both","duration":1,"autoreverses":false,"timingFunction":"EaseInEaseOut","property":"zPosition","to":{"scalar":0.014}}],"fillMode":"both","autoreverses":false,"duration":1}],"initialState":{"affineTransform":[1,0,0,1,0,0],"masksToBounds":false,"rotation":0,"scale":1,"position":{"pointX":273.46871084659904,"pointY":612.01235384128404},"width":390.43989181518555,"sublayerTransform":[1,0,0,0,0,1,0,0,0,0,1,0,0,0,0,1],"contentsRect":{"y":0,"x":0,"width":1,"height":1},"opacity":1,"edgeAntialiasingMask":251658240,"height":188.99999856948853,"hidden":false,"anchorPoint":{"pointX":0.5,"pointY":0.5}},"layers":[{"animations":[{"timeOffset":0,"beginTime":0,"repeatCount":0,"animations":[{"timeOffset":0,"from":{"texture":"5C7BF4DB61D4F8109096B2599DB2A9D9"},"beginTime":0,"repeatCount":0,"fillMode":"both","duration":1,"autoreverses":false,"timingFunction":"EaseInEaseOut","property":"contents","to":{"texture":"5C7BF4DB61D4F8109096B2599DB2A9D9"}},{"timeOffset":0,"from":{"pointX":0,"pointY":0},"beginTime":0,"repeatCount":0,"fillMode":"both","duration":1,"autoreverses":false,"timingFunction":"EaseInEaseOut","property":"transform.translation","to":{"pointX":-11,"pointY":-791}}],"fillMode":"both","autoreverses":false,"duration":1}],"layers":[],"texturedRectangle":{"singleTextureOpacity":1,"textXHeight":0.42976744186046512,"textBaseline":0.74122004600964597,"isBackgroundTexture":true,"isVerticalText":false,"textColor":[0,0,0,1],"textureType":6},"initialState":{"affineTransform":[1,0,0,1,0,0],"masksToBounds":false,"rotation":0,"scale":1,"position":{"pointX":195.21994018554688,"pointY":94.5},"width":292,"sublayerTransform":[1,0,0,0,0,1,0,0,0,0,1,0,0,0,0,1],"contentsRect":{"y":0,"x":0,"width":1,"height":1},"opacity":1,"edgeAntialiasingMask":0,"height":43,"hidden":false,"anchorPoint":{"pointX":0.50160515453614085,"pointY":0.256101268756739}},"texture":"5C7BF4DB61D4F8109096B2599DB2A9D9"}]},{"animations":[{"timeOffset":0,"beginTime":0,"repeatCount":0,"animations":[{"timeOffset":0,"from":{"scalar":0.014},"beginTime":0,"repeatCount":0,"fillMode":"both","duration":1,"autoreverses":false,"timingFunction":"EaseInEaseOut","property":"zPosition","to":{"scalar":0.0070000000000000001}}],"fillMode":"both","autoreverses":false,"duration":1}],"initialState":{"affineTransform":[1,0,0,1,0,0],"masksToBounds":false,"rotation":0,"scale":1,"position":{"pointX":491.41280555725098,"pointY":855.34863699019843},"width":923.43997955322266,"sublayerTransform":[1,0,0,0,0,1,0,0,0,0,1,0,0,0,0,1],"contentsRect":{"y":0,"x":0,"width":1,"height":1},"opacity":1,"edgeAntialiasingMask":251658240,"height":62.999999523162842,"hidden":false,"anchorPoint":{"pointX":0.5,"pointY":0.5}},"layers":[{"animations":[{"timeOffset":0,"beginTime":0,"repeatCount":0,"animations":[{"timeOffset":0,"from":{"texture":"A859F6D6A591DE66D362599897966C1B"},"beginTime":0,"repeatCount":0,"fillMode":"both","duration":1,"autoreverses":false,"timingFunction":"EaseInEaseOut","property":"contents","to":{"texture":"C8739BB44A636A445C17349105AF9D78"}},{"timeOffset":0,"from":{"pointX":0,"pointY":0},"beginTime":0,"repeatCount":0,"fillMode":"both","duration":1,"autoreverses":false,"timingFunction":"EaseInEaseOut","property":"transform.translation","to":{"pointX":9.9999999999999432,"pointY":-773}}],"fillMode":"both","autoreverses":false,"duration":1}],"layers":[],"texturedRectangle":{"singleTextureOpacity":1,"textXHeight":0.42976744186046512,"textBaseline":0.74904057326725604,"isBackgroundTexture":true,"isVerticalText":false,"textColor":[0,0,0,1],"textureType":6},"initialState":{"affineTransform":[1,0,0,1,0,0],"masksToBounds":false,"rotation":0,"scale":1,"position":{"pointX":461.72000000000014,"pointY":31.5},"width":916,"sublayerTransform":[1,0,0,0,0,1,0,0,0,0,1,0,0,0,0,1],"contentsRect":{"y":0,"x":0,"width":1,"height":1},"opacity":1,"edgeAntialiasingMask":0,"height":43,"hidden":false,"anchorPoint":{"pointX":0.50045067224960671,"pointY":0.44996830764225598}},"texture":"A859F6D6A591DE66D362599897966C1B"}]},{"animations":[{"timeOffset":0,"beginTime":0,"repeatCount":0,"animations":[{"timeOffset":0,"from":{"scalar":0.014999999999999999},"beginTime":0,"repeatCount":0,"fillMode":"both","duration":1,"autoreverses":false,"timingFunction":"EaseInEaseOut","property":"zPosition","to":{"scalar":0.014999999999999999}}],"fillMode":"both","autoreverses":false,"duration":1}],"initialState":{"affineTransform":[1,0,0,1,0,0],"masksToBounds":false,"rotation":0,"scale":1,"position":{"pointX":509.04761409759521,"pointY":-700.47982025146484},"width":911.8800163269043,"sublayerTransform":[1,0,0,0,0,1,0,0,0,0,1,0,0,0,0,1],"contentsRect":{"y":0,"x":0,"width":1,"height":1},"opacity":1,"edgeAntialiasingMask":251658240,"height":62.999999523162842,"hidden":false,"anchorPoint":{"pointX":0.5,"pointY":0.5}},"layers":[{"animations":[{"timeOffset":0,"beginTime":0,"repeatCount":0,"animations":[{"timeOffset":0,"from":{"scalar":1},"beginTime":0,"repeatCount":0,"fillMode":"forwards","duration":0.33329999999999999,"autoreverses":false,"timingFunction":"EaseInEaseOut","property":"opacity","to":{"scalar":0}},{"timeOffset":0,"from":{"scalar":true},"beginTime":0.33329999999999999,"repeatCount":0,"fillMode":"forwards","property":"hidden","autoreverses":false,"duration":0.66670000000000007,"to":{"scalar":true}}],"fillMode":"both","autoreverses":false,"duration":1}],"layers":[],"texturedRectangle":{"singleTextureOpacity":1,"textXHeight":0.41999999999999998,"textBaseline":0.73591562292792578,"isBackgroundTexture":true,"isVerticalText":false,"textColor":[0,0,0,1],"textureType":6},"initialState":{"affineTransform":[1,0,0,1,0,0],"masksToBounds":false,"rotation":0,"scale":1,"position":{"pointX":455.94000000000017,"pointY":31.5},"width":900,"sublayerTransform":[1,0,0,0,0,1,0,0,0,0,1,0,0,0,0,1],"contentsRect":{"y":0,"x":0,"width":1,"height":1},"opacity":1,"edgeAntialiasingMask":0,"height":44,"hidden":false,"anchorPoint":{"pointX":0.49894178437127024,"pointY":0.44364045424894855}},"texture":"73CDDF1532160B82087D02DFB58251FF"}]},{"animations":[{"timeOffset":0,"beginTime":0,"repeatCount":0,"animations":[{"timeOffset":0,"from":{"scalar":0.016},"beginTime":0,"repeatCount":0,"fillMode":"both","duration":1,"autoreverses":false,"timingFunction":"EaseInEaseOut","property":"zPosition","to":{"scalar":0.016}}],"fillMode":"both","autoreverses":false,"duration":1}],"initialState":{"affineTransform":[1,0,0,1,0,0],"masksToBounds":false,"rotation":0,"scale":1,"position":{"pointX":549.30142116546631,"pointY":-357.43212890625},"width":843.18194580078125,"sublayerTransform":[1,0,0,0,0,1,0,0,0,0,1,0,0,0,0,1],"contentsRect":{"y":0,"x":0,"width":1,"height":1},"opacity":1,"edgeAntialiasingMask":251658240,"height":562.82391357421875,"hidden":false,"anchorPoint":{"pointX":0.5,"pointY":0.5}},"layers":[{"animations":[{"timeOffset":0,"beginTime":0,"repeatCount":0,"animations":[{"timeOffset":0,"from":{"scalar":1},"beginTime":0,"repeatCount":0,"fillMode":"forwards","duration":0.33329999999999999,"autoreverses":false,"timingFunction":"EaseInEaseOut","property":"opacity","to":{"scalar":0}},{"timeOffset":0,"from":{"scalar":true},"beginTime":0.33329999999999999,"repeatCount":0,"fillMode":"forwards","property":"hidden","autoreverses":false,"duration":0.66670000000000007,"to":{"scalar":true}}],"fillMode":"both","autoreverses":false,"duration":1}],"layers":[],"texturedRectangle":{"isBackgroundTexture":true,"singleTextureOpacity":1,"textureType":5,"textBaseline":0,"textXHeight":0,"isVerticalText":false},"initialState":{"affineTransform":[1,0,0,1,0,0],"masksToBounds":false,"rotation":0,"scale":1,"position":{"pointX":421.59097290039062,"pointY":281.41195678710938},"width":846,"sublayerTransform":[1,0,0,0,0,1,0,0,0,0,1,0,0,0,0,1],"contentsRect":{"y":0,"x":0,"width":1,"height":1},"opacity":1,"edgeAntialiasingMask":0,"height":565,"hidden":false,"anchorPoint":{"pointX":0.5003562897936954,"pointY":0.50012012582964605}},"texture":"50A60D786241F61E51AC87B06DB956ED"}]},{"animations":[{"timeOffset":0,"beginTime":0,"repeatCount":0,"animations":[{"timeOffset":0,"from":{"scalar":0.017000000000000001},"beginTime":0,"repeatCount":0,"fillMode":"both","duration":1,"autoreverses":false,"timingFunction":"EaseInEaseOut","property":"zPosition","to":{"scalar":0.017000000000000001}}],"fillMode":"both","autoreverses":false,"duration":1}],"initialState":{"affineTransform":[1,0,0,1,0,0],"masksToBounds":false,"rotation":0,"scale":1,"position":{"pointX":501.42003519970649,"pointY":1482.948840777234},"width":1024,"sublayerTransform":[1,0,0,0,0,1,0,0,0,0,1,0,0,0,0,1],"contentsRect":{"y":0,"x":0,"width":1,"height":1},"opacity":1,"edgeAntialiasingMask":251658240,"height":90.6875,"hidden":false,"anchorPoint":{"pointX":0.5,"pointY":0.5}},"layers":[{"animations":[{"timeOffset":0,"beginTime":0,"repeatCount":0,"animations":[{"timeOffset":0,"from":{"scalar":0},"beginTime":0.66670000000000007,"repeatCount":0,"fillMode":"both","duration":0.33329999999999999,"autoreverses":false,"timingFunction":"EaseInEaseOut","property":"opacity","to":{"scalar":1}},{"timeOffset":0,"from":{"scalar":false},"beginTime":0.66670000000000007,"repeatCount":0,"fillMode":"forwards","property":"hidden","autoreverses":false,"duration":0.33329999999999993,"to":{"scalar":false}}],"fillMode":"both","autoreverses":false,"duration":1}],"layers":[],"texturedRectangle":{"isBackgroundTexture":true,"singleTextureOpacity":1,"textureType":5,"textBaseline":0,"textXHeight":0,"isVerticalText":false},"initialState":{"affineTransform":[1,0,0,1,0,0],"masksToBounds":false,"rotation":0,"scale":1,"position":{"pointX":512,"pointY":45.343574523925781},"width":1027,"sublayerTransform":[1,0,0,0,0,1,0,0,0,0,1,0,0,0,0,1],"contentsRect":{"y":0,"x":0,"width":1,"height":1},"opacity":1,"edgeAntialiasingMask":0,"height":94,"hidden":true,"anchorPoint":{"pointX":0.49992213748754283,"pointY":0.49945388618255038}},"texture":"FC4FEE615C6DD4F71D0AF1DA00C8E4DF"}]},{"animations":[{"timeOffset":0,"beginTime":0,"repeatCount":0,"animations":[{"timeOffset":0,"from":{"scalar":0.018000000000000002},"beginTime":0,"repeatCount":0,"fillMode":"both","duration":1,"autoreverses":false,"timingFunction":"EaseInEaseOut","property":"zPosition","to":{"scalar":0.018000000000000002}}],"fillMode":"both","autoreverses":false,"duration":1}],"initialState":{"affineTransform":[1,0,0,1,0,0],"masksToBounds":false,"rotation":0,"scale":1,"position":{"pointX":105.09865461856523,"pointY":841.16399733240348},"width":161.67999505996704,"sublayerTransform":[1,0,0,0,0,1,0,0,0,0,1,0,0,0,0,1],"contentsRect":{"y":0,"x":0,"width":1,"height":1},"opacity":1,"edgeAntialiasingMask":251658240,"height":62.999999523162842,"hidden":false,"anchorPoint":{"pointX":0.5,"pointY":0.5}},"layers":[{"animations":[{"timeOffset":0,"beginTime":0,"repeatCount":0,"animations":[{"timeOffset":0,"from":{"scalar":0},"beginTime":0.66670000000000007,"repeatCount":0,"fillMode":"both","duration":0.33329999999999999,"autoreverses":false,"timingFunction":"EaseInEaseOut","property":"opacity","to":{"scalar":1}},{"timeOffset":0,"from":{"scalar":false},"beginTime":0.66670000000000007,"repeatCount":0,"fillMode":"forwards","property":"hidden","autoreverses":false,"duration":0.33329999999999993,"to":{"scalar":false}}],"fillMode":"both","autoreverses":false,"duration":1}],"layers":[],"texturedRectangle":{"singleTextureOpacity":1,"textXHeight":0.52800000000000002,"textBaseline":0.91497442836277321,"isBackgroundTexture":true,"isVerticalText":false,"textColor":[0,0,0,1],"textureType":6},"initialState":{"affineTransform":[1,0,0,1,0,0],"masksToBounds":false,"rotation":0,"scale":1,"position":{"pointX":80.840000000000003,"pointY":31.5},"width":151,"sublayerTransform":[1,0,0,0,0,1,0,0,0,0,1,0,0,0,0,1],"contentsRect":{"y":0,"x":0,"width":1,"height":1},"opacity":1,"edgeAntialiasingMask":0,"height":35,"hidden":true,"anchorPoint":{"pointX":0.50396461648067359,"pointY":0.54754278773777321}},"texture":"D652167B412906357E3CE351B7717F53"}]},{"animations":[{"timeOffset":0,"beginTime":0,"repeatCount":0,"animations":[{"timeOffset":0,"from":{"scalar":0.019},"beginTime":0,"repeatCount":0,"fillMode":"both","duration":1,"autoreverses":false,"timingFunction":"EaseInEaseOut","property":"zPosition","to":{"scalar":0.019}}],"fillMode":"both","autoreverses":false,"duration":1}],"initialState":{"affineTransform":[1,0,0,1,0,0],"masksToBounds":false,"rotation":0,"scale":1,"position":{"pointX":479.34493338138259,"pointY":1063.5924383800721},"width":371.8472900390625,"sublayerTransform":[1,0,0,0,0,1,0,0,0,0,1,0,0,0,0,1],"contentsRect":{"y":0,"x":0,"width":1,"height":1},"opacity":1,"edgeAntialiasingMask":251658240,"height":370.12776947021484,"hidden":false,"anchorPoint":{"pointX":0.5,"pointY":0.5}},"layers":[{"animations":[{"timeOffset":0,"beginTime":0,"repeatCount":0,"animations":[{"timeOffset":0,"from":{"scalar":0},"beginTime":0.66670000000000007,"repeatCount":0,"fillMode":"both","duration":0.33329999999999999,"autoreverses":false,"timingFunction":"EaseInEaseOut","property":"opacity","to":{"scalar":1}},{"timeOffset":0,"from":{"scalar":false},"beginTime":0.66670000000000007,"repeatCount":0,"fillMode":"forwards","property":"hidden","autoreverses":false,"duration":0.33329999999999993,"to":{"scalar":false}}],"fillMode":"both","autoreverses":false,"duration":1}],"layers":[],"texturedRectangle":{"isBackgroundTexture":true,"singleTextureOpacity":1,"textureType":5,"textBaseline":0,"textXHeight":0,"isVerticalText":false},"initialState":{"affineTransform":[1,0,0,1,0,0],"masksToBounds":false,"rotation":0,"scale":1,"position":{"pointX":185.92364501953125,"pointY":185.06388473510742},"width":375,"sublayerTransform":[1,0,0,0,0,1,0,0,0,0,1,0,0,0,0,1],"contentsRect":{"y":0,"x":0,"width":1,"height":1},"opacity":1,"edgeAntialiasingMask":0,"height":373,"hidden":true,"anchorPoint":{"pointX":0.49958648901702024,"pointY":0.50024782407526025}},"texture":"57C6ABAACAB1520BA4F51129C02428B9"}]},{"animations":[{"timeOffset":0,"beginTime":0,"repeatCount":0,"animations":[{"timeOffset":0,"from":{"scalar":0.02},"beginTime":0,"repeatCount":0,"fillMode":"both","duration":1,"autoreverses":false,"timingFunction":"EaseInEaseOut","property":"zPosition","to":{"scalar":0.02}}],"fillMode":"both","autoreverses":false,"duration":1}],"initialState":{"affineTransform":[1,0,0,1,0,0],"masksToBounds":false,"rotation":0,"scale":1,"position":{"pointX":479.34317862064046,"pointY":1356.380359331921},"width":514.07709121704102,"sublayerTransform":[1,0,0,0,0,1,0,0,0,0,1,0,0,0,0,1],"contentsRect":{"y":0,"x":0,"width":1,"height":1},"opacity":1,"edgeAntialiasingMask":251658240,"height":117.99999475479126,"hidden":false,"anchorPoint":{"pointX":0.5,"pointY":0.5}},"layers":[{"animations":[{"timeOffset":0,"beginTime":0,"repeatCount":0,"animations":[{"timeOffset":0,"from":{"scalar":0},"beginTime":0.66670000000000007,"repeatCount":0,"fillMode":"both","duration":0.33329999999999999,"autoreverses":false,"timingFunction":"EaseInEaseOut","property":"opacity","to":{"scalar":1}},{"timeOffset":0,"from":{"scalar":false},"beginTime":0.66670000000000007,"repeatCount":0,"fillMode":"forwards","property":"hidden","autoreverses":false,"duration":0.33329999999999993,"to":{"scalar":false}}],"fillMode":"both","autoreverses":false,"duration":1}],"layers":[],"texturedRectangle":{"singleTextureOpacity":1,"textXHeight":0.42976744186046512,"textBaseline":0.73815045061396212,"isBackgroundTexture":true,"isVerticalText":false,"textColor":[0,0,0,1],"textureType":6},"initialState":{"affineTransform":[1,0,0,1,0,0],"masksToBounds":false,"rotation":0,"scale":1,"position":{"pointX":257.03854370117188,"pointY":59},"width":483,"sublayerTransform":[1,0,0,0,0,1,0,0,0,0,1,0,0,0,0,1],"contentsRect":{"y":0,"x":0,"width":1,"height":1},"opacity":1,"edgeAntialiasingMask":0,"height":43,"hidden":true,"anchorPoint":{"pointX":0.49967531410619426,"pointY":-0.20045669873196814}},"texture":"9B9E3FF61C6DA97BCFC9137737E378E4"}]},{"animations":[{"timeOffset":0,"beginTime":0,"repeatCount":0,"animations":[{"timeOffset":0,"from":{"scalar":0.021000000000000001},"beginTime":0,"repeatCount":0,"fillMode":"both","duration":1,"autoreverses":false,"timingFunction":"EaseInEaseOut","property":"zPosition","to":{"scalar":0.021000000000000001}}],"fillMode":"both","autoreverses":false,"duration":1}],"initialState":{"affineTransform":[1,0,0,1,0,0],"masksToBounds":false,"rotation":0,"scale":1,"position":{"pointX":479.34317862064046,"pointY":1356.380359331921},"width":514.07709121704102,"sublayerTransform":[1,0,0,0,0,1,0,0,0,0,1,0,0,0,0,1],"contentsRect":{"y":0,"x":0,"width":1,"height":1},"opacity":1,"edgeAntialiasingMask":251658240,"height":117.99999475479126,"hidden":false,"anchorPoint":{"pointX":0.5,"pointY":0.5}},"layers":[{"animations":[{"timeOffset":0,"beginTime":0,"repeatCount":0,"animations":[{"timeOffset":0,"from":{"scalar":0},"beginTime":0.66670000000000007,"repeatCount":0,"fillMode":"both","duration":0.33329999999999999,"autoreverses":false,"timingFunction":"EaseInEaseOut","property":"opacity","to":{"scalar":1}},{"timeOffset":0,"from":{"scalar":false},"beginTime":0.66670000000000007,"repeatCount":0,"fillMode":"forwards","property":"hidden","autoreverses":false,"duration":0.33329999999999993,"to":{"scalar":false}}],"fillMode":"both","autoreverses":false,"duration":1}],"layers":[],"texturedRectangle":{"singleTextureOpacity":1,"textXHeight":0.42976744186046512,"textBaseline":0.73815045061396212,"isBackgroundTexture":true,"isVerticalText":false,"textColor":[0,0,0,1],"textureType":6},"initialState":{"affineTransform":[1,0,0,1,0,0],"masksToBounds":false,"rotation":0,"scale":1,"position":{"pointX":257.03854370117188,"pointY":59},"width":502,"sublayerTransform":[1,0,0,0,0,1,0,0,0,0,1,0,0,0,0,1],"contentsRect":{"y":0,"x":0,"width":1,"height":1},"opacity":1,"edgeAntialiasingMask":0,"height":43,"hidden":true,"anchorPoint":{"pointX":0.50068361895078051,"pointY":1.0786130687098923}},"texture":"CAFED3AF2045F50E77B4C5EF057C0296"}]}]},"effects":[],"duration":1,"type":"transition","name":"apple:magic-move-implied-motion-path","objectID":"0"}],"automaticPlay":false,"hyperlinks":[],"accessibility":[{"text":"pasted-image.tiff","targetRectangle":{"y":-638.84408569335938,"x":127.71044826507568,"width":843.18194580078125,"height":562.82391357421875}},{"text":"Problema: limitacin de salvoconductos para verificacin de madera transportada","targetRectangle":{"y":53.867806229466026,"x":3.5199794309345975,"width":1015.9599999999998,"height":110}},{"text":"A las personas les importa comprar madera ilegal?","targetRectangle":{"y":827.84863722861701,"x":34.192815780639648,"width":914.44000000000028,"height":55}},{"text":"Reto 1: pases oficiales en el proceso de transporte.","targetRectangle":{"y":-727.97982001304626,"x":57.607605934143066,"width":902.88000000000034,"height":55}},{"text":"pasted-image.tiff","targetRectangle":{"y":201.75257777039855,"x":61.06246066404136,"width":424.82192993164062,"height":281.875}},{"text":"pasted-image.tiff","targetRectangle":{"y":168.40517604575109,"x":561.68202540018603,"width":390.43988037109386,"height":534.087158203125}},{"text":"Quantum","targetRectangle":{"y":-0.88781028985977173,"x":3.4599555730819702,"width":58.884,"height":19}},{"text":"47% de la madera que se vende en Colombia es ilegal","targetRectangle":{"y":521.51235455653978,"x":95.622705124553136,"width":366.09199999999998,"height":181}},{"text":"QUANTUM","targetRectangle":{"y":2.5121692419052124,"x":6.2139547729492186,"width":42.069999999999993,"height":14.200042724609375}}],"baseLayer":{"animations":[],"initialState":{"affineTransform":[1,0,0,1,0,0],"masksToBounds":false,"rotation":0,"scale":1,"position":{"pointX":512,"pointY":384},"width":1024,"sublayerTransform":[1,0,0,0,0,1,0,0,0,0,1,0,0,0,0,1],"contentsRect":{"y":0,"x":0,"width":1,"height":1},"opacity":1,"edgeAntialiasingMask":251658240,"height":768,"hidden":false,"anchorPoint":{"pointX":0.5,"pointY":0.5}},"objectID":"0","layers":[{"animations":[],"initialState":{"affineTransform":[1,0,0,1,0,0],"masksToBounds":false,"rotation":0,"scale":1,"position":{"pointX":512,"pointY":384},"width":1024,"sublayerTransform":[1,0,0,0,0,1,0,0,0,0,1,-0.00049229876906403734,0,0,0,1],"contentsRect":{"y":0,"x":0,"width":1,"height":1},"opacity":1,"edgeAntialiasingMask":251658240,"height":768,"hidden":false,"anchorPoint":{"pointX":0.5,"pointY":0.5}},"layers":[{"animations":[],"initialState":{"affineTransform":[1,0,0,1,0,0],"masksToBounds":false,"rotation":0,"scale":1,"position":{"pointX":512,"pointY":384},"width":1024,"sublayerTransform":[1,0,0,0,0,1,0,0,0,0,1,0,0,0,0,1],"contentsRect":{"y":0,"x":0,"width":1,"height":1},"opacity":1,"edgeAntialiasingMask":251658240,"height":768,"hidden":false,"anchorPoint":{"pointX":0.5,"pointY":0.5}},"layers":[{"animations":[],"layers":[],"texturedRectangle":{"isBackgroundTexture":true,"singleTextureOpacity":1,"textureType":1,"textBaseline":0,"textXHeight":0,"isVerticalText":false},"initialState":{"affineTransform":[1,0,0,1,0,0],"masksToBounds":false,"rotation":0,"scale":1,"position":{"pointX":512,"pointY":384},"width":1024,"sublayerTransform":[1,0,0,0,0,1,0,0,0,0,1,0,0,0,0,1],"contentsRect":{"y":0,"x":0,"width":1,"height":1},"opacity":1,"edgeAntialiasingMask":0,"height":768,"hidden":false,"anchorPoint":{"pointX":0.5,"pointY":0.5}},"texture":"498E23C82CA78A4BCD7BA88E5243B6FC"}]}]},{"animations":[],"initialState":{"affineTransform":[1,0,0,1,0,0],"masksToBounds":false,"rotation":0,"scale":1,"position":{"pointX":511.99999995400589,"pointY":108.86780360686166},"width":1024.9600410461426,"sublayerTransform":[1,0,0,0,0,1,0,0,0,0,1,0,0,0,0,1],"contentsRect":{"y":0,"x":0,"width":1,"height":1},"opacity":1,"edgeAntialiasingMask":251658240,"height":117.99999475479126,"hidden":false,"anchorPoint":{"pointX":0.5,"pointY":0.5}},"layers":[{"animations":[],"layers":[],"texturedRectangle":{"singleTextureOpacity":1,"textXHeight":0.41999999999999998,"textBaseline":0.75517985571229607,"isBackgroundTexture":true,"isVerticalText":false,"textColor":[0,0,0,1],"textureType":6},"initialState":{"affineTransform":[1,0,0,1,0,0],"masksToBounds":false,"rotation":0,"scale":1,"position":{"pointX":512.48000000000002,"pointY":59},"width":1003,"sublayerTransform":[1,0,0,0,0,1,0,0,0,0,1,0,0,0,0,1],"contentsRect":{"y":0,"x":0,"width":1,"height":1},"opacity":1,"edgeAntialiasingMask":0,"height":44,"hidden":false,"anchorPoint":{"pointX":0.5054835288444014,"pointY":1.0879046870333189}},"texture":"7997E8F06BC201E039EF065E93082D88"}]},{"animations":[],"initialState":{"affineTransform":[1,0,0,1,0,0],"masksToBounds":false,"rotation":0,"scale":1,"position":{"pointX":511.99999995400589,"pointY":108.86780360686166},"width":1024.9600410461426,"sublayerTransform":[1,0,0,0,0,1,0,0,0,0,1,0,0,0,0,1],"contentsRect":{"y":0,"x":0,"width":1,"height":1},"opacity":1,"edgeAntialiasingMask":251658240,"height":117.99999475479126,"hidden":false,"anchorPoint":{"pointX":0.5,"pointY":0.5}},"layers":[{"animations":[],"layers":[],"texturedRectangle":{"singleTextureOpacity":1,"textXHeight":0.42976744186046512,"textBaseline":0.74948636398467505,"isBackgroundTexture":true,"isVerticalText":false,"textColor":[0,0,0,1],"textureType":6},"initialState":{"affineTransform":[1,0,0,1,0,0],"masksToBounds":false,"rotation":0,"scale":1,"position":{"pointX":512.48000000000002,"pointY":59},"width":429,"sublayerTransform":[1,0,0,0,0,1,0,0,0,0,1,0,0,0,0,1],"contentsRect":{"y":0,"x":0,"width":1,"height":1},"opacity":1,"edgeAntialiasingMask":0,"height":43,"hidden":false,"anchorPoint":{"pointX":1.1841491362026448,"pointY":-0.18912078536125521}},"texture":"A6B3E55D8D49AFA75C517C767C9F662E"}]},{"animations":[],"initialState":{"affineTransform":[1,0,0,1,0,0],"masksToBounds":false,"rotation":0,"scale":1,"position":{"pointX":32.901954650878906,"pointY":8.6121902465820312},"width":67.883998155593872,"sublayerTransform":[1,0,0,0,0,1,0,0,0,0,1,0,0,0,0,1],"contentsRect":{"y":0,"x":0,"width":1,"height":1},"opacity":1,"edgeAntialiasingMask":251658240,"height":27.000001072883606,"hidden":false,"anchorPoint":{"pointX":0.5,"pointY":0.5}},"layers":[{"animations":[],"layers":[],"texturedRectangle":{"singleTextureOpacity":1,"textXHeight":0.43119999999999997,"textBaseline":0.7992151538530986,"isBackgroundTexture":true,"isVerticalText":false,"textColor":[0,0,0,1],"textureType":6},"initialState":{"affineTransform":[1,0,0,1,0,0],"masksToBounds":false,"rotation":0,"scale":1,"position":{"pointX":33.942,"pointY":13.5},"width":61,"sublayerTransform":[1,0,0,0,0,1,0,0,0,0,1,0,0,0,0,1],"contentsRect":{"y":0,"x":0,"width":1,"height":1},"opacity":1,"edgeAntialiasingMask":0,"height":15,"hidden":false,"anchorPoint":{"pointX":0.50658943562429459,"pointY":0.50747931400934854}},"texture":"3AF23A742D6F1B28B161D01517090E4F"}]},{"animations":[],"initialState":{"affineTransform":[1,0,0,1,0,0],"masksToBounds":false,"rotation":0,"scale":1,"position":{"pointX":511.99998772144312,"pointY":7.6676045656204224},"width":1023.4651489257814,"sublayerTransform":[1,0,0,0,0,1,0,0,0,0,1,0,0,0,0,1],"contentsRect":{"y":0,"x":0,"width":1,"height":1},"opacity":1,"edgeAntialiasingMask":251658240,"height":16.630849838256836,"hidden":false,"anchorPoint":{"pointX":0.5,"pointY":0.5}},"layers":[{"animations":[],"layers":[],"texturedRectangle":{"singleTextureOpacity":1,"textXHeight":0,"shapePath":{"lineWidth":1,"flatness":0.59999999999999998,"lineCapStyle":0,"elements":[{"type":"MoveToPoint","points":[[1.2674132585524376,1.3521796464920044]]},{"type":"AddLine","points":[[1024.7325621843338,1.3521796464920044]]},{"type":"AddLine","points":[[1024.7325621843338,17.98302948474884]]},{"type":"AddLine","points":[[1.2674132585524376,17.98302948474884]]},{"type":"CloseSubpath"},{"type":"MoveToPoint","points":[[1.2674132585524376,1.3521796464920044]]}],"windingRule":0,"lineJoinStyle":0,"miterLimit":10},"isBackgroundTexture":true,"textBaseline":0,"isVerticalText":false,"textureType":5},"initialState":{"affineTransform":[1,0,0,1,0,0],"masksToBounds":false,"rotation":0,"scale":1,"position":{"pointX":511.73257446289074,"pointY":8.315424919128418},"width":1026,"sublayerTransform":[1,0,0,0,0,1,0,0,0,0,1,0,0,0,0,1],"contentsRect":{"y":0,"x":0,"width":1,"height":1},"opacity":1,"edgeAntialiasingMask":0,"height":19,"hidden":false,"anchorPoint":{"pointX":0.49999998803259571,"pointY":0.50882129292739064}},"texture":"E857BD603F7117228C43533A0180CA60"}]},{"animations":[],"initialState":{"affineTransform":[1,0,0,1,0,0],"masksToBounds":false,"rotation":0,"scale":1,"position":{"pointX":511.99999502301216,"pointY":17.612190008163452},"width":1023.4338989257812,"sublayerTransform":[1,0,0,0,0,1,0,0,0,0,1,0,0,0,0,1],"contentsRect":{"y":0,"x":0,"width":1,"height":1},"opacity":1,"edgeAntialiasingMask":251658240,"height":4.6500544548034686,"hidden":false,"anchorPoint":{"pointX":0.5,"pointY":0.5}},"layers":[{"animations":[],"layers":[],"texturedRectangle":{"singleTextureOpacity":1,"textXHeight":0,"shapePath":{"lineWidth":1,"flatness":0.59999999999999998,"lineCapStyle":0,"elements":[{"type":"MoveToPoint","points":[[1.2830455601215363,1.287162780761717]]},{"type":"AddLine","points":[[1024.7169444859028,1.287162780761717]]},{"type":"AddLine","points":[[1024.7169444859028,5.9372172355651855]]},{"type":"AddLine","points":[[1.2830455601215363,5.9372172355651855]]},{"type":"CloseSubpath"},{"type":"MoveToPoint","points":[[1.2830455601215363,1.287162780761717]]}],"windingRule":0,"lineJoinStyle":0,"miterLimit":10},"isBackgroundTexture":true,"textBaseline":0,"isVerticalText":false,"textureType":5},"initialState":{"affineTransform":[1,0,0,1,0,0],"masksToBounds":false,"rotation":0,"scale":1,"position":{"pointX":511.71694946289062,"pointY":2.3250272274017352},"width":1026,"sublayerTransform":[1,0,0,0,0,1,0,0,0,0,1,0,0,0,0,1],"contentsRect":{"y":0,"x":0,"width":1,"height":1},"opacity":1,"edgeAntialiasingMask":0,"height":7,"hidden":false,"anchorPoint":{"pointX":0.49999999514913468,"pointY":0.51602714402335026}},"texture":"923CA22559BCC412D89FDB110EC58F93"}]},{"animations":[],"initialState":{"affineTransform":[1,0,0,1,0,0],"masksToBounds":false,"rotation":0,"scale":1,"position":{"pointX":27.248954296112061,"pointY":9.6121902465820312},"width":82.319998741149902,"sublayerTransform":[1,0,0,0,0,1,0,0,0,0,1,0,0,0,0,1],"contentsRect":{"y":0,"x":0,"width":1,"height":1},"opacity":1,"edgeAntialiasingMask":251658240,"height":22.200042009353638,"hidden":false,"anchorPoint":{"pointX":0.5,"pointY":0.5}},"layers":[{"animations":[],"layers":[],"texturedRectangle":{"singleTextureOpacity":1,"textXHeight":0.50700000000000001,"textBaseline":0.83430646998541691,"isBackgroundTexture":true,"isVerticalText":false,"textColor":[0.81037485599517822,0.69284248352050781,0.229374960064888,1],"textureType":6},"initialState":{"affineTransform":[1,0,0,1,0,0],"masksToBounds":false,"rotation":0,"scale":1,"position":{"pointX":41.159999847412109,"pointY":11.100021362304688},"width":45,"sublayerTransform":[1,0,0,0,0,1,0,0,0,0,1,0,0,0,0,1],"contentsRect":{"y":0,"x":0,"width":1,"height":1},"opacity":1,"edgeAntialiasingMask":0,"height":14,"hidden":false,"anchorPoint":{"pointX":0.49442121717664933,"pointY":0.61515647172927856}},"texture":"19D39F26BBF3E99701402A4CD6C8EC2E"}]},{"animations":[],"initialState":{"affineTransform":[1,0,0,1,0,0],"masksToBounds":false,"rotation":0,"scale":1,"position":{"pointX":501.42003516390469,"pointY":-681.67416593350288},"width":1024.9600410461426,"sublayerTransform":[1,0,0,0,0,1,0,0,0,0,1,0,0,0,0,1],"contentsRect":{"y":0,"x":0,"width":1,"height":1},"opacity":1,"edgeAntialiasingMask":251658240,"height":117.99999475479126,"hidden":false,"anchorPoint":{"pointX":0.5,"pointY":0.5}},"layers":[{"animations":[],"layers":[],"texturedRectangle":{"singleTextureOpacity":1,"textXHeight":0.41999999999999998,"textBaseline":0.74286236615855661,"isBackgroundTexture":true,"isVerticalText":false,"textColor":[0,0,0,1],"textureType":6},"initialState":{"affineTransform":[1,0,0,1,0,0],"masksToBounds":false,"rotation":0,"scale":1,"position":{"pointX":512.48000000000002,"pointY":59},"width":1003,"sublayerTransform":[1,0,0,0,0,1,0,0,0,0,1,0,0,0,0,1],"contentsRect":{"y":0,"x":0,"width":1,"height":1},"opacity":1,"edgeAntialiasingMask":0,"height":44,"hidden":true,"anchorPoint":{"pointX":0.50590230771768041,"pointY":1.0755871974795794}},"texture":"7997E8F06BC201E039EF065E93082D88"}]},{"animations":[],"initialState":{"affineTransform":[1,0,0,1,0,0],"masksToBounds":false,"rotation":0,"scale":1,"position":{"pointX":501.42003516390469,"pointY":-681.67416593350288},"width":1024.9600410461426,"sublayerTransform":[1,0,0,0,0,1,0,0,0,0,1,0,0,0,0,1],"contentsRect":{"y":0,"x":0,"width":1,"height":1},"opacity":1,"edgeAntialiasingMask":251658240,"height":117.99999475479126,"hidden":false,"anchorPoint":{"pointX":0.5,"pointY":0.5}},"layers":[{"animations":[],"layers":[],"texturedRectangle":{"singleTextureOpacity":1,"textXHeight":0.54352941176470593,"textBaseline":0.93193953267577923,"isBackgroundTexture":true,"isVerticalText":false,"textColor":[0,0,0,1],"textureType":6},"initialState":{"affineTransform":[1,0,0,1,0,0],"masksToBounds":false,"rotation":0,"scale":1,"position":{"pointX":512.48000000000002,"pointY":59},"width":191,"sublayerTransform":[1,0,0,0,0,1,0,0,0,0,1,0,0,0,0,1],"contentsRect":{"y":0,"x":0,"width":1,"height":1},"opacity":1,"edgeAntialiasingMask":0,"height":34,"hidden":true,"anchorPoint":{"pointX":2.661884893407505,"pointY":-0.25512245032054431}},"texture":"6F35A2FA386A392D32E7D14B03912335"}]},{"animations":[],"initialState":{"affineTransform":[1,0,0,1,0,0],"masksToBounds":false,"rotation":0,"scale":1,"position":{"pointX":273.47342562986165,"pointY":342.69007777039855},"width":424.82192993164062,"sublayerTransform":[1,0,0,0,0,1,0,0,0,0,1,0,0,0,0,1],"contentsRect":{"y":0,"x":0,"width":1,"height":1},"opacity":1,"edgeAntialiasingMask":251658240,"height":281.875,"hidden":false,"anchorPoint":{"pointX":0.5,"pointY":0.5}},"layers":[{"animations":[],"layers":[],"texturedRectangle":{"isBackgroundTexture":true,"singleTextureOpacity":1,"textureType":5,"textBaseline":0,"textXHeight":0,"isVerticalText":false},"initialState":{"affineTransform":[1,0,0,1,0,0],"masksToBounds":false,"rotation":0,"scale":1,"position":{"pointX":212.41096496582028,"pointY":140.93539712589518},"width":427,"sublayerTransform":[1,0,0,0,0,1,0,0,0,0,1,0,0,0,0,1],"contentsRect":{"y":0,"x":0,"width":1,"height":1},"opacity":1,"edgeAntialiasingMask":0,"height":285,"hidden":false,"anchorPoint":{"pointX":0.49993776494112802,"pointY":0.50065956103962705}},"texture":"D8677BC1273213678DD6CACBA39C3DD2"}]},{"animations":[],"initialState":{"affineTransform":[1,0,0,1,0,0],"masksToBounds":false,"rotation":0,"scale":1,"position":{"pointX":756.90196558573302,"pointY":435.44875514731359},"width":390.43988037109386,"sublayerTransform":[1,0,0,0,0,1,0,0,0,0,1,0,0,0,0,1],"contentsRect":{"y":0,"x":0,"width":1,"height":1},"opacity":1,"edgeAntialiasingMask":251658240,"height":534.087158203125,"hidden":false,"anchorPoint":{"pointX":0.5,"pointY":0.5}},"layers":[{"animations":[],"layers":[],"texturedRectangle":{"isBackgroundTexture":true,"singleTextureOpacity":1,"textureType":5,"textBaseline":0,"textXHeight":0,"isVerticalText":false},"initialState":{"affineTransform":[1,0,0,1,0,0],"masksToBounds":false,"rotation":0,"scale":1,"position":{"pointX":195.21994018554688,"pointY":267.0435791015625},"width":394,"sublayerTransform":[1,0,0,0,0,1,0,0,0,0,1,0,0,0,0,1],"contentsRect":{"y":0,"x":0,"width":1,"height":1},"opacity":1,"edgeAntialiasingMask":0,"height":537,"hidden":false,"anchorPoint":{"pointX":0.49975118168967742,"pointY":0.49990457196892663}},"texture":"7BF16B539769317ED1409CCE8CBC5605"}]},{"animations":[],"initialState":{"affineTransform":[1,0,0,1,0,0],"masksToBounds":false,"rotation":0,"scale":1,"position":{"pointX":273.46871084659904,"pointY":612.01235384128404},"width":390.43989181518555,"sublayerTransform":[1,0,0,0,0,1,0,0,0,0,1,0,0,0,0,1],"contentsRect":{"y":0,"x":0,"width":1,"height":1},"opacity":1,"edgeAntialiasingMask":251658240,"height":188.99999856948853,"hidden":false,"anchorPoint":{"pointX":0.5,"pointY":0.5}},"layers":[{"animations":[],"layers":[],"texturedRectangle":{"singleTextureOpacity":1,"textXHeight":0.42976744186046512,"textBaseline":0.74122004600964597,"isBackgroundTexture":true,"isVerticalText":false,"textColor":[0,0,0,1],"textureType":6},"initialState":{"affineTransform":[1,0,0,1,0,0],"masksToBounds":false,"rotation":0,"scale":1,"position":{"pointX":195.21994018554688,"pointY":94.5},"width":328,"sublayerTransform":[1,0,0,0,0,1,0,0,0,0,1,0,0,0,0,1],"contentsRect":{"y":0,"x":0,"width":1,"height":1},"opacity":1,"edgeAntialiasingMask":0,"height":43,"hidden":false,"anchorPoint":{"pointX":0.50142897903827177,"pointY":-1.0229684986851215}},"texture":"B3ECAFF3A25943E1D6C4CCDF2DB4608C"}]},{"animations":[],"initialState":{"affineTransform":[1,0,0,1,0,0],"masksToBounds":false,"rotation":0,"scale":1,"position":{"pointX":273.46871084659904,"pointY":612.01235384128404},"width":390.43989181518555,"sublayerTransform":[1,0,0,0,0,1,0,0,0,0,1,0,0,0,0,1],"contentsRect":{"y":0,"x":0,"width":1,"height":1},"opacity":1,"edgeAntialiasingMask":251658240,"height":188.99999856948853,"hidden":false,"anchorPoint":{"pointX":0.5,"pointY":0.5}},"layers":[{"animations":[],"layers":[],"texturedRectangle":{"singleTextureOpacity":1,"textXHeight":0.56727272727272726,"textBaseline":0.92001123193130174,"isBackgroundTexture":true,"isVerticalText":false,"textColor":[0.96236997842788696,0.82058531045913696,0.27432787418365479,1],"textureType":6},"initialState":{"affineTransform":[1,0,0,1,0,0],"masksToBounds":false,"rotation":0,"scale":1,"position":{"pointX":195.21994018554688,"pointY":94.5},"width":355,"sublayerTransform":[1,0,0,0,0,1,0,0,0,0,1,0,0,0,0,1],"contentsRect":{"y":0,"x":0,"width":1,"height":1},"opacity":1,"edgeAntialiasingMask":0,"height":44,"hidden":false,"anchorPoint":{"pointX":0.49991184542127642,"pointY":1.7957353308304496}},"texture":"E7ED5F39F9B284E3C82B24F9FA28837A"}]},{"animations":[],"initialState":{"affineTransform":[1,0,0,1,0,0],"masksToBounds":false,"rotation":0,"scale":1,"position":{"pointX":273.46871084659904,"pointY":612.01235384128404},"width":390.43989181518555,"sublayerTransform":[1,0,0,0,0,1,0,0,0,0,1,0,0,0,0,1],"contentsRect":{"y":0,"x":0,"width":1,"height":1},"opacity":1,"edgeAntialiasingMask":251658240,"height":188.99999856948853,"hidden":false,"anchorPoint":{"pointX":0.5,"pointY":0.5}},"layers":[{"animations":[],"layers":[],"texturedRectangle":{"singleTextureOpacity":1,"textXHeight":0.42976744186046512,"textBaseline":0.74122004600964597,"isBackgroundTexture":true,"isVerticalText":false,"textColor":[0,0,0,1],"textureType":6},"initialState":{"affineTransform":[1,0,0,1,0,0],"masksToBounds":false,"rotation":0,"scale":1,"position":{"pointX":195.21994018554688,"pointY":94.5},"width":292,"sublayerTransform":[1,0,0,0,0,1,0,0,0,0,1,0,0,0,0,1],"contentsRect":{"y":0,"x":0,"width":1,"height":1},"opacity":1,"edgeAntialiasingMask":0,"height":43,"hidden":false,"anchorPoint":{"pointX":0.50160515453614085,"pointY":0.256101268756739}},"texture":"5C7BF4DB61D4F8109096B2599DB2A9D9"}]},{"animations":[],"initialState":{"affineTransform":[1,0,0,1,0,0],"masksToBounds":false,"rotation":0,"scale":1,"position":{"pointX":491.41280555725098,"pointY":855.34863699019843},"width":923.43997955322266,"sublayerTransform":[1,0,0,0,0,1,0,0,0,0,1,0,0,0,0,1],"contentsRect":{"y":0,"x":0,"width":1,"height":1},"opacity":1,"edgeAntialiasingMask":251658240,"height":62.999999523162842,"hidden":false,"anchorPoint":{"pointX":0.5,"pointY":0.5}},"layers":[{"animations":[],"layers":[],"texturedRectangle":{"singleTextureOpacity":1,"textXHeight":0.42976744186046512,"textBaseline":0.74904057326725604,"isBackgroundTexture":true,"isVerticalText":false,"textColor":[0,0,0,1],"textureType":6},"initialState":{"affineTransform":[1,0,0,1,0,0],"masksToBounds":false,"rotation":0,"scale":1,"position":{"pointX":461.72000000000014,"pointY":31.5},"width":916,"sublayerTransform":[1,0,0,0,0,1,0,0,0,0,1,0,0,0,0,1],"contentsRect":{"y":0,"x":0,"width":1,"height":1},"opacity":1,"edgeAntialiasingMask":0,"height":43,"hidden":false,"anchorPoint":{"pointX":0.50045067224960671,"pointY":0.44996830764225598}},"texture":"A859F6D6A591DE66D362599897966C1B"}]},{"animations":[],"initialState":{"affineTransform":[1,0,0,1,0,0],"masksToBounds":false,"rotation":0,"scale":1,"position":{"pointX":509.04761409759521,"pointY":-700.47982025146484},"width":911.8800163269043,"sublayerTransform":[1,0,0,0,0,1,0,0,0,0,1,0,0,0,0,1],"contentsRect":{"y":0,"x":0,"width":1,"height":1},"opacity":1,"edgeAntialiasingMask":251658240,"height":62.999999523162842,"hidden":false,"anchorPoint":{"pointX":0.5,"pointY":0.5}},"layers":[{"animations":[],"layers":[],"texturedRectangle":{"singleTextureOpacity":1,"textXHeight":0.41999999999999998,"textBaseline":0.73591562292792578,"isBackgroundTexture":true,"isVerticalText":false,"textColor":[0,0,0,1],"textureType":6},"initialState":{"affineTransform":[1,0,0,1,0,0],"masksToBounds":false,"rotation":0,"scale":1,"position":{"pointX":455.94000000000017,"pointY":31.5},"width":900,"sublayerTransform":[1,0,0,0,0,1,0,0,0,0,1,0,0,0,0,1],"contentsRect":{"y":0,"x":0,"width":1,"height":1},"opacity":1,"edgeAntialiasingMask":0,"height":44,"hidden":false,"anchorPoint":{"pointX":0.49894178437127024,"pointY":0.44364045424894855}},"texture":"73CDDF1532160B82087D02DFB58251FF"}]},{"animations":[],"initialState":{"affineTransform":[1,0,0,1,0,0],"masksToBounds":false,"rotation":0,"scale":1,"position":{"pointX":549.30142116546631,"pointY":-357.43212890625},"width":843.18194580078125,"sublayerTransform":[1,0,0,0,0,1,0,0,0,0,1,0,0,0,0,1],"contentsRect":{"y":0,"x":0,"width":1,"height":1},"opacity":1,"edgeAntialiasingMask":251658240,"height":562.82391357421875,"hidden":false,"anchorPoint":{"pointX":0.5,"pointY":0.5}},"layers":[{"animations":[],"layers":[],"texturedRectangle":{"isBackgroundTexture":true,"singleTextureOpacity":1,"textureType":5,"textBaseline":0,"textXHeight":0,"isVerticalText":false},"initialState":{"affineTransform":[1,0,0,1,0,0],"masksToBounds":false,"rotation":0,"scale":1,"position":{"pointX":421.59097290039062,"pointY":281.41195678710938},"width":846,"sublayerTransform":[1,0,0,0,0,1,0,0,0,0,1,0,0,0,0,1],"contentsRect":{"y":0,"x":0,"width":1,"height":1},"opacity":1,"edgeAntialiasingMask":0,"height":565,"hidden":false,"anchorPoint":{"pointX":0.5003562897936954,"pointY":0.50012012582964605}},"texture":"50A60D786241F61E51AC87B06DB956ED"}]},{"animations":[],"initialState":{"affineTransform":[1,0,0,1,0,0],"masksToBounds":false,"rotation":0,"scale":1,"position":{"pointX":501.42003519970649,"pointY":1482.948840777234},"width":1024,"sublayerTransform":[1,0,0,0,0,1,0,0,0,0,1,0,0,0,0,1],"contentsRect":{"y":0,"x":0,"width":1,"height":1},"opacity":1,"edgeAntialiasingMask":251658240,"height":90.6875,"hidden":false,"anchorPoint":{"pointX":0.5,"pointY":0.5}},"layers":[{"animations":[],"layers":[],"texturedRectangle":{"isBackgroundTexture":true,"singleTextureOpacity":1,"textureType":5,"textBaseline":0,"textXHeight":0,"isVerticalText":false},"initialState":{"affineTransform":[1,0,0,1,0,0],"masksToBounds":false,"rotation":0,"scale":1,"position":{"pointX":512,"pointY":45.343574523925781},"width":1027,"sublayerTransform":[1,0,0,0,0,1,0,0,0,0,1,0,0,0,0,1],"contentsRect":{"y":0,"x":0,"width":1,"height":1},"opacity":1,"edgeAntialiasingMask":0,"height":94,"hidden":true,"anchorPoint":{"pointX":0.49992213748754283,"pointY":0.49945388618255038}},"texture":"FC4FEE615C6DD4F71D0AF1DA00C8E4DF"}]},{"animations":[],"initialState":{"affineTransform":[1,0,0,1,0,0],"masksToBounds":false,"rotation":0,"scale":1,"position":{"pointX":105.09865461856523,"pointY":841.16399733240348},"width":161.67999505996704,"sublayerTransform":[1,0,0,0,0,1,0,0,0,0,1,0,0,0,0,1],"contentsRect":{"y":0,"x":0,"width":1,"height":1},"opacity":1,"edgeAntialiasingMask":251658240,"height":62.999999523162842,"hidden":false,"anchorPoint":{"pointX":0.5,"pointY":0.5}},"layers":[{"animations":[],"layers":[],"texturedRectangle":{"singleTextureOpacity":1,"textXHeight":0.52800000000000002,"textBaseline":0.91497442836277321,"isBackgroundTexture":true,"isVerticalText":false,"textColor":[0,0,0,1],"textureType":6},"initialState":{"affineTransform":[1,0,0,1,0,0],"masksToBounds":false,"rotation":0,"scale":1,"position":{"pointX":80.840000000000003,"pointY":31.5},"width":151,"sublayerTransform":[1,0,0,0,0,1,0,0,0,0,1,0,0,0,0,1],"contentsRect":{"y":0,"x":0,"width":1,"height":1},"opacity":1,"edgeAntialiasingMask":0,"height":35,"hidden":true,"anchorPoint":{"pointX":0.50396461648067359,"pointY":0.54754278773777321}},"texture":"D652167B412906357E3CE351B7717F53"}]},{"animations":[],"initialState":{"affineTransform":[1,0,0,1,0,0],"masksToBounds":false,"rotation":0,"scale":1,"position":{"pointX":479.34493338138259,"pointY":1063.5924383800721},"width":371.8472900390625,"sublayerTransform":[1,0,0,0,0,1,0,0,0,0,1,0,0,0,0,1],"contentsRect":{"y":0,"x":0,"width":1,"height":1},"opacity":1,"edgeAntialiasingMask":251658240,"height":370.12776947021484,"hidden":false,"anchorPoint":{"pointX":0.5,"pointY":0.5}},"layers":[{"animations":[],"layers":[],"texturedRectangle":{"isBackgroundTexture":true,"singleTextureOpacity":1,"textureType":5,"textBaseline":0,"textXHeight":0,"isVerticalText":false},"initialState":{"affineTransform":[1,0,0,1,0,0],"masksToBounds":false,"rotation":0,"scale":1,"position":{"pointX":185.92364501953125,"pointY":185.06388473510742},"width":375,"sublayerTransform":[1,0,0,0,0,1,0,0,0,0,1,0,0,0,0,1],"contentsRect":{"y":0,"x":0,"width":1,"height":1},"opacity":1,"edgeAntialiasingMask":0,"height":373,"hidden":true,"anchorPoint":{"pointX":0.49958648901702024,"pointY":0.50024782407526025}},"texture":"57C6ABAACAB1520BA4F51129C02428B9"}]},{"animations":[],"initialState":{"affineTransform":[1,0,0,1,0,0],"masksToBounds":false,"rotation":0,"scale":1,"position":{"pointX":479.34317862064046,"pointY":1356.380359331921},"width":514.07709121704102,"sublayerTransform":[1,0,0,0,0,1,0,0,0,0,1,0,0,0,0,1],"contentsRect":{"y":0,"x":0,"width":1,"height":1},"opacity":1,"edgeAntialiasingMask":251658240,"height":117.99999475479126,"hidden":false,"anchorPoint":{"pointX":0.5,"pointY":0.5}},"layers":[{"animations":[],"layers":[],"texturedRectangle":{"singleTextureOpacity":1,"textXHeight":0.42976744186046512,"textBaseline":0.73815045061396212,"isBackgroundTexture":true,"isVerticalText":false,"textColor":[0,0,0,1],"textureType":6},"initialState":{"affineTransform":[1,0,0,1,0,0],"masksToBounds":false,"rotation":0,"scale":1,"position":{"pointX":257.03854370117188,"pointY":59},"width":483,"sublayerTransform":[1,0,0,0,0,1,0,0,0,0,1,0,0,0,0,1],"contentsRect":{"y":0,"x":0,"width":1,"height":1},"opacity":1,"edgeAntialiasingMask":0,"height":43,"hidden":true,"anchorPoint":{"pointX":0.49967531410619426,"pointY":-0.20045669873196814}},"texture":"9B9E3FF61C6DA97BCFC9137737E378E4"}]},{"animations":[],"initialState":{"affineTransform":[1,0,0,1,0,0],"masksToBounds":false,"rotation":0,"scale":1,"position":{"pointX":479.34317862064046,"pointY":1356.380359331921},"width":514.07709121704102,"sublayerTransform":[1,0,0,0,0,1,0,0,0,0,1,0,0,0,0,1],"contentsRect":{"y":0,"x":0,"width":1,"height":1},"opacity":1,"edgeAntialiasingMask":251658240,"height":117.99999475479126,"hidden":false,"anchorPoint":{"pointX":0.5,"pointY":0.5}},"layers":[{"animations":[],"layers":[],"texturedRectangle":{"singleTextureOpacity":1,"textXHeight":0.42976744186046512,"textBaseline":0.73815045061396212,"isBackgroundTexture":true,"isVerticalText":false,"textColor":[0,0,0,1],"textureType":6},"initialState":{"affineTransform":[1,0,0,1,0,0],"masksToBounds":false,"rotation":0,"scale":1,"position":{"pointX":257.03854370117188,"pointY":59},"width":502,"sublayerTransform":[1,0,0,0,0,1,0,0,0,0,1,0,0,0,0,1],"contentsRect":{"y":0,"x":0,"width":1,"height":1},"opacity":1,"edgeAntialiasingMask":0,"height":43,"hidden":true,"anchorPoint":{"pointX":0.50068361895078051,"pointY":1.0786130687098923}},"texture":"CAFED3AF2045F50E77B4C5EF057C0296"}]}]}}]}